tz/osemosys/__init__.py
tz/osemosys/defaults.py
tz/osemosys/exceptions.py
tz/osemosys/logger.py
tz/osemosys/io/__init__.py
tz/osemosys/io/load_model.py
tz/osemosys/io/simpleeval.py
tz/osemosys/model/__init__.py
tz/osemosys/model/model.py
tz/osemosys/model/objective.py
tz/osemosys/model/solution.py
tz/osemosys/model/constraints/__init__.py
tz/osemosys/model/constraints/_accounting_technology.py
tz/osemosys/model/constraints/_capital_costs.py
tz/osemosys/model/constraints/_operating_costs.py
tz/osemosys/model/constraints/_salvage_value.py
tz/osemosys/model/constraints/_total_discounted_costs.py
tz/osemosys/model/constraints/annual_activity.py
tz/osemosys/model/constraints/annual_capacity_factor_min.py
tz/osemosys/model/constraints/capacity_adequacy_a.py
tz/osemosys/model/constraints/capacity_adequacy_b.py
tz/osemosys/model/constraints/capacity_growth_rate.py
tz/osemosys/model/constraints/emissions.py
tz/osemosys/model/constraints/energy_balance_a.py
tz/osemosys/model/constraints/energy_balance_b.py
tz/osemosys/model/constraints/new_capacity.py
tz/osemosys/model/constraints/re_targets.py
tz/osemosys/model/constraints/regiongroup.py
tz/osemosys/model/constraints/reserve_margin.py
tz/osemosys/model/constraints/storage.py
tz/osemosys/model/constraints/total_activity.py
tz/osemosys/model/constraints/total_capacity.py
tz/osemosys/model/constraints/trade.py
tz/osemosys/model/linear_expressions/__init__.py
tz/osemosys/model/linear_expressions/activity.py
tz/osemosys/model/linear_expressions/capacity.py
tz/osemosys/model/linear_expressions/discounting.py
tz/osemosys/model/linear_expressions/emissions.py
tz/osemosys/model/linear_expressions/financials.py
tz/osemosys/model/linear_expressions/production.py
tz/osemosys/model/linear_expressions/re_production.py
tz/osemosys/model/linear_expressions/regiongroup.py
tz/osemosys/model/linear_expressions/reserve_margin.py
tz/osemosys/model/linear_expressions/storage.py
tz/osemosys/model/linear_expressions/trade.py
tz_osemosys-0.3.6.dist-info/licenses/LICENSE
tz_osemosys-0.3.6.dist-info/METADATA
tz_osemosys-0.3.6.dist-info/WHEEL
tz_osemosys-0.3.6.dist-info/top_level.txt
tz_osemosys-0.3.6.dist-info/RECORD
