Metadata-Version: 2.4
Name: tz-osemosys
Version: 0.3.6
Summary: An OSeMOSYS implementation for Scenario Builder by TransitionZero
Author-email: Lucas Kruitwagen <lucas.kruitwagen@gmail.com>, Edward Terpilowski-Gill <edwardxtg@gmail.com>, Abhishek Shivakumar <abhishek0208@gmail.com>
Project-URL: Homepage, https://github.com/transition-zero/tz-osemosys
Project-URL: Bug Reports, https://github.com/transition-zero/tz-osemosys/issues
Project-URL: Funding, https://transitionzero.org
Project-URL: Source, https://github.com/transition-zero/tz-osemosys
Keywords: energy,milp,climate
Classifier: Development Status :: 3 - Alpha
Classifier: Intended Audience :: Science/Research
Classifier: Topic :: Scientific/Engineering
Classifier: License :: OSI Approved :: GNU Affero General Public License v3
Classifier: Programming Language :: Python :: 3.11
Classifier: Programming Language :: Python :: 3 :: Only
Requires-Python: >=3.11
License-File: LICENSE
Requires-Dist: pydantic>2
Requires-Dist: pydantic-settings
Requires-Dist: xarray
Requires-Dist: orjson
Requires-Dist: linopy==0.5.5
Requires-Dist: h5netcdf
Provides-Extra: dev
Requires-Dist: pre-commit; extra == "dev"
Requires-Dist: black; extra == "dev"
Requires-Dist: pytest; extra == "dev"
Requires-Dist: pytest-order; extra == "dev"
Requires-Dist: pytest-cov; extra == "dev"
Requires-Dist: pytest-asyncio; extra == "dev"
Requires-Dist: mypy; extra == "dev"
Requires-Dist: tox; extra == "dev"
Requires-Dist: coverage; extra == "dev"
Requires-Dist: highspy; extra == "dev"
Provides-Extra: cloudpath
Requires-Dist: cloudpathlib[all]; extra == "cloudpath"
Dynamic: license-file
